ietools/Decision.py
ietools/EnggEcon.py
ietools/Inventory.py
ietools/__init__.py
ietools/utils.py
ietools-0.1.dist-info/LICENSE
ietools-0.1.dist-info/METADATA
ietools-0.1.dist-info/WHEEL
ietools-0.1.dist-info/top_level.txt
ietools-0.1.dist-info/RECORD
