Metadata-Version: 2.1
Name: ietools
Version: 0.1
Summary: A package implementing commonly used Industrial Engineering and Management tools
Author-email: Gana Natarajn <gana1984@gmail.com>
License: MIT License        
Project-URL: Bug Tracker, https://github.com/gana1984/ietools/issues
Project-URL: Homepage, https://github.com/gana1984/ietools
Keywords: industrial engineering,management,ie
Classifier: Programming Language :: Python :: 3
Classifier: Development Status :: 3 - Alpha
Classifier: License :: OSI Approved :: MIT License
Classifier: Operating System :: OS Independent
Requires-Python: >=3.8
License-File: LICENSE
